tkvideoutils/__init__.py
tkvideoutils/tkvideoutils.py
tkVideoUtils-1.2.10.dist-info/LICENSE
tkVideoUtils-1.2.10.dist-info/METADATA
tkVideoUtils-1.2.10.dist-info/WHEEL
tkVideoUtils-1.2.10.dist-info/top_level.txt
tkVideoUtils-1.2.10.dist-info/RECORD
