Metadata-Version: 2.1
Name: tkVideoUtils
Version: 1.2.10
Summary: Python module for playing and recording videos with sound inside tkinter Label widget using Pillow, imageio, and PyAudio, including media playback control, slider, and fps aware buffering.
Home-page: https://github.com/wsarce/tkVideoUtils
Author: Walker Arce (wsarce)
Author-email: wsarcera@gmail.com
License: MIT
Keywords: tkVideoUtils tkinter video webcam display label pillow imageio wsarce sound
Classifier: License :: OSI Approved :: MIT License
Classifier: Programming Language :: Python :: 3.8
Classifier: Topic :: Multimedia :: Video :: Display
License-File: LICENSE
